[{"name": "Saad Hasaneen", "formatted_address": "11 Abd Al Aziz Al Beshri, El-Bostan, Heliopolis, Cairo Governorate, Egypt", "lat": 30.1054698, "lng": 31.3240607, "types": ["point_of_interest", "establishment"], "place_id": "ChIJNW9zvZEVWBQR3xHce5if3mw"}, {"name": "Abaza Square", "formatted_address": "11 Abd Al Aziz Al Beshri, El-Bostan, Heliopolis, Cairo Governorate, Egypt", "lat": 30.1043338, "lng": 31.3235289, "types": ["point_of_interest", "establishment"], "place_id": "ChIJdz6PX1oVWBQRsmR8xSpy-JY"}, {"name": "Home", "formatted_address": "11 Abd Al Aziz Al Beshri, El-Bostan, Heliopolis, Cairo Governorate, Egypt", "lat": 30.10437, "lng": 31.32355, "types": ["point_of_interest", "establishment"], "place_id": "ChIJzyZSAhgVWBQRzISbQSiJnrM"}, {"name": "El Nabawy", "formatted_address": "11 Abd Al Aziz Al Beshri, El-Bostan, Heliopolis, Cairo Governorate, Egypt", "lat": 30.1054698, "lng": 31.3240607, "types": ["mosque", "place_of_worship", "point_of_interest", "establishment"], "place_id": "ChIJNWRevZEVWBQR3p4bDGV9KNI"}, {"name": "Sh-Electronics", "formatted_address": "11 Abd Al Aziz Al Beshri, El-Bostan, Heliopolis, Cairo Governorate, Egypt", "lat": 30.1052803, "lng": 31.3233569, "types": ["point_of_interest", "establishment"], "place_id": "ChIJYW7suZEVWBQRoFII8DLs7c0"}, {"name": "مكتب المستشار المالي سامي مقلد محاسبون ومراجعون", "formatted_address": "18 عبد العزيز البشري، البستان، قسم مصر الجديدة،، Cairo Governorate, Egypt", "lat": 30.1045289, "lng": 31.3238078, "types": ["point_of_interest", "establishment"], "place_id": "ChIJr9NDOVcVWBQRe6OergWq0wE"}, {"name": "دار مناسبات مسجد التقوى", "formatted_address": "7 Abd Al Aziz Al Beshri, El-Bostan, Heliopolis, Cairo Governorate, Egypt", "lat": 30.105355, "lng": 31.32440159999999, "types": ["point_of_interest", "establishment"], "place_id": "ChIJY8AXl5EVWBQRkqVdFCgbPik"}, {"name": "ادارة مصر الجديدة البيطرية", "formatted_address": "البرج السكاني والتجاري - ب، 11 عبد العزيز البشري، البستان، قسم مصر الجديدة،، Cairo Governorate, Egypt", "lat": 30.1043204, "lng": 31.323552, "types": ["point_of_interest", "establishment"], "place_id": "ChIJmV_quroVWBQRB_AePU75Sag"}, {"name": "مدرسة البشري الابتدائية المشتركة", "formatted_address": "1 Abd Al Aziz Al Beshri, El-Zaytoun El-Bahareya, Heliopolis, Cairo Governorate, Egypt", "lat": 30.1053897, "lng": 31.3247868, "types": ["point_of_interest", "establishment"], "place_id": "ChIJvQKqlpgVWBQR2y84r8p4AA0"}, {"name": "أبراج مصر الجديدة للاسكان و التعمير برج 11 أ", "formatted_address": "11 Abd Al Aziz Al Beshri, El-Bostan, Heliopolis, Cairo Governorate, Egypt", "lat": 30.1043425, "lng": 31.3234971, "types": ["point_of_interest", "establishment"], "place_id": "ChIJwbIBEcYVWBQRJ3qcUysCOaE"}, {"name": "نقابة الأطباء البيطريين الفرعية", "formatted_address": "6 Abd Al Aziz Al Beshri, El-Bostan, Heliopolis, Cairo Governorate, Egypt", "lat": 30.1048014, "lng": 31.3244624, "types": ["point_of_interest", "establishment"], "place_id": "ChIJ1xZpFsoVWBQR7QK0OkLFdC8"}, {"name": "Tyson the legend", "formatted_address": "7 Abd Al Aziz Al Beshri, El-Bostan, Heliopolis, Cairo Governorate, Egypt", "lat": 30.1052815, "lng": 31.3245314, "types": ["gym", "health", "point_of_interest", "establishment"], "place_id": "ChIJW_HYTHoVWBQRjKTZQZiXOcE"}, {"name": "Makan Real Estate", "formatted_address": "13 Abd Al Aziz Al Beshri, El-Bostan, Heliopolis, Cairo Governorate, Egypt", "lat": 30.104302, "lng": 31.3238503, "types": ["point_of_interest", "establishment"], "place_id": "ChIJ80rh4b8VWBQRBad717Pdzek"}, {"name": "مسجد الرحمة", "formatted_address": "11 Abd Al Aziz Al Beshri, El-Bostan, Heliopolis, Cairo Governorate, Egypt", "lat": 30.1028051, "lng": 31.3229833, "types": ["mosque", "place_of_worship", "point_of_interest", "establishment"], "place_id": "ChIJx7q_Lo4VWBQRdkj9vSUoFRA"}, {"name": "مستشفى المعلمين التخصصى", "formatted_address": "6 Abd Al Aziz Al Beshri, El-Zaytoun El-Bahareya, Heliopolis, Cairo Governorate, Egypt", "lat": 30.1031655, "lng": 31.3218376, "types": ["hospital", "health", "point_of_interest", "establishment"], "place_id": "ChIJ__9Luu0_WBQRKDBiaEcluMQ"}, {"name": "Square Cafe", "formatted_address": "5 Abd Al Aziz Al Beshri, El-Bostan, Heliopolis, Cairo Governorate, Egypt", "lat": 30.1034551, "lng": 31.3227597, "types": ["cafe", "food", "point_of_interest", "establishment"], "place_id": "ChIJC4N81I8VWBQRmoK4oME70Jo"}, {"name": "El Taqwa Specialized Hospital", "formatted_address": "6 Abd Al Aziz Al Beshri, El-Bostan, Heliopolis, Cairo Governorate, Egypt", "lat": 30.1051568, "lng": 31.3240639, "types": ["hospital", "health", "point_of_interest", "establishment"], "place_id": "ChIJm5EWuZEVWBQRIeEe_Enx6hg"}, {"name": "مساكن ابوبكر الصديق", "formatted_address": "بجوار مستشفي التقوي, مساكن ابو بكر الصديق, شارع Abd Al Aziz Al Beshri, Egypt", "lat": 30.1051568, "lng": 31.3240639, "types": ["lodging", "point_of_interest", "establishment"], "place_id": "ChIJTwZAfGoVWBQRIOvkv_JNqhE"}, {"name": "El Central Garden - حديقة السنترال", "formatted_address": "8 Abaza Square, البستان، قسم مصر الجديدة، محافظة القاهرة‬،،, El-Bostan, Heliopolis, Cairo Governorate, Egypt", "lat": 30.10389309999999, "lng": 31.3231162, "types": ["park", "point_of_interest", "establishment"], "place_id": "ChIJMUIa61cVWBQRGhNzfUMc8tI"}, {"name": "K Group Show Room", "formatted_address": "37 Ismail El Falaky, El-Bostan, Heliopolis, Cairo Governorate, Egypt", "lat": 30.105028, "lng": 31.324777, "types": ["point_of_interest", "establishment"], "place_id": "ChIJwZeYr20VWBQR7-lwyoQrQ_k"}, {"name": "أسواق شارع عبد العزيز فرع جسر السويس", "formatted_address": "Gesr Al Suez, El-Montaza, Heliopolis, Cairo Governorate, Egypt", "lat": 30.0986967, "lng": 31.3144895, "types": ["electronics_store", "point_of_interest", "store", "establishment"], "place_id": "ChIJZ8kITAEVWBQR5EUo50Ap9oQ"}, {"name": "Supermarket Mido", "formatted_address": "19 Abd Al Aziz Al Beshri, El-Bostan, Heliopolis, Cairo Governorate, Egypt", "lat": 30.1045625, "lng": 31.3243846, "types": ["grocery_or_supermarket", "food", "point_of_interest", "store", "establishment"], "place_id": "ChIJAQDE65EVWBQRWa8OuLd_vq8"}, {"name": "اللؤلؤة", "formatted_address": "شارع جسر السويس،مصر الجديدة،قسم، Heliopolis, Egypt", "lat": 30.1050849, "lng": 31.3231419, "types": ["cafe", "food", "point_of_interest", "establishment"], "place_id": "ChIJZZTGyZEVWBQRSGExDIU3CqI"}, {"name": "سما تورز ايجيبت", "formatted_address": "4 ش Helmy Eissa, El-Bostan, Heliopolis, Cairo Governorate, Egypt", "lat": 30.1028564, "lng": 31.3222398, "types": ["point_of_interest", "establishment"], "place_id": "ChIJVVXByY8VWBQRDx9BQuJH-Z4"}, {"name": "Abrag For Contracting & Real Estate Investment", "formatted_address": "220 ش جسر السويس، Ain Shams Sharkeya, Zeitoun, Cairo Governorate, Egypt", "lat": 30.1044815, "lng": 31.3215771, "types": ["point_of_interest", "establishment"], "place_id": "ChIJ4w8XE4YWWBQRISp-5c9zqO4"}, {"name": "Pubg Car care", "formatted_address": "ش Abd Al Aziz Al Beshri, El-Bostan, Heliopolis, Cairo Governorate, Egypt", "lat": 30.102994, "lng": 31.3217948, "types": ["car_wash", "point_of_interest", "establishment"], "place_id": "ChIJYW68JygVWBQRQwRNHvUPkhQ"}, {"name": "بيوتى سنتر ياسمين", "formatted_address": "11 Abd Al Aziz Al Beshri, El-Bostan, Heliopolis, Cairo Governorate, Egypt", "lat": 30.1051191, "lng": 31.3231852, "types": ["beauty_salon", "point_of_interest", "establishment"], "place_id": "ChIJK2DFt5EVWBQRVH2LwZPpntM"}, {"name": "23 Ventitre Cafe & Mart", "formatted_address": "11 Abd Al Aziz Al Beshri, El-Bostan, Heliopolis, Cairo Governorate, Egypt", "lat": 30.1042938, "lng": 31.3235808, "types": ["cafe", "food", "point_of_interest", "establishment"], "place_id": "ChIJD4xb15EVWBQRbxfxMIgZyo4"}, {"name": "First For Trade & Distribution", "formatted_address": "1 ش السباق، El-Bostan, Heliopolis, Cairo Governorate, Egypt", "lat": 30.1021056, "lng": 31.3223778, "types": ["point_of_interest", "establishment"], "place_id": "ChIJObn4rY8VWBQR7Kz1t4N2PYU"}, {"name": "معمل الأسنان", "formatted_address": "1 Abd Al Aziz Al Beshri, El-Bostan, Heliopolis, Cairo Governorate, Egypt", "lat": 30.1053854, "lng": 31.3247972, "types": ["dentist", "health", "point_of_interest", "establishment"], "place_id": "ChIJyVNhhZEVWBQRPYOLaTbD21c"}, {"name": "It Solutions", "formatted_address": "10 ميدان اباظة، El-Bostan, Heliopolis, Cairo Governorate, Egypt", "lat": 30.10393569999999, "lng": 31.3223704, "types": ["point_of_interest", "establishment"], "place_id": "ChIJMafaK44VWBQR9dP5CpuWtdY"}, {"name": "El Mostakbal Library", "formatted_address": "Gesr Al Suez, El-Bostan, Heliopolis, Cairo Governorate, Egypt", "lat": 30.1033445, "lng": 31.3214739, "types": ["library", "point_of_interest", "establishment"], "place_id": "ChIJg7jRw48VWBQRNQWRbC5j6xE"}, {"name": "هامكو للتجارة", "formatted_address": "16 ش Abd Al Aziz Al Beshri, El-Bostan, Heliopolis, Cairo Governorate, Egypt", "lat": 30.103535, "lng": 31.322373, "types": ["point_of_interest", "store", "establishment"], "place_id": "ChIJIR_s8R8VWBQRpRJhZJJXzBA"}, {"name": "Segraph Advertising", "formatted_address": "13 El Mahkama Sq.، El-Bostan, Heliopolis, Cairo Governorate, Egypt", "lat": 30.1037, "lng": 31.3249, "types": ["point_of_interest", "establishment"], "place_id": "ChIJpczCxZIVWBQRprmOvCjVjHo"}, {"name": "Catalonian Trade Promotion Center - COPCA Egypt", "formatted_address": "6 Al Sebaq, El-Bostan, Heliopolis, Cairo Governorate, Egypt", "lat": 30.102522, "lng": 31.32227899999999, "types": ["point_of_interest", "establishment"], "place_id": "ChIJebW-to8VWBQRJVgbNsA9U2Q"}, {"name": "FBC (Fady Badwi Clinic)", "formatted_address": "20 Abd Al Aziz Al Beshri, El-Bostan, Heliopolis, Cairo Governorate, Egypt", "lat": 30.1051009, "lng": 31.3236912, "types": ["dentist", "health", "point_of_interest", "establishment"], "place_id": "ChIJPdejrZcVWBQR9FC7cxBKM8g"}, {"name": "K GROUP", "formatted_address": "37 Ismail El Falaky, El-Bostan, Heliopolis, Cairo Governorate, Egypt", "lat": 30.1049164, "lng": 31.3247868, "types": ["point_of_interest", "establishment"], "place_id": "ChIJ7xLRhPoVWBQR199gu437QPo"}, {"name": "Osama William accounting Office", "formatted_address": "11 Abd Al Aziz Al Beshri, El-Bostan, Heliopolis, Cairo Governorate, Egypt", "lat": 30.104319, "lng": 31.3235376, "types": ["accounting", "finance", "point_of_interest", "establishment"], "place_id": "ChIJ1wuwLPsVWBQRpC4ZkjDdqek"}, {"name": "Centeral Heliopolis ( Gesr Al Suez )", "formatted_address": "El-Bostan, Heliopolis, Cairo Governorate, Egypt", "lat": 30.104212, "lng": 31.321724, "types": ["transit_station", "point_of_interest", "establishment"], "place_id": "ChIJD_uh2I8VWBQRLcTYF1zhlM0"}, {"name": "El Mostafa Central", "formatted_address": "34 ش احمد خليل، El-Zaytoun El-Bahareya, Zeitoun, Cairo Governorate, Egypt", "lat": 30.105049, "lng": 31.32190899999999, "types": ["point_of_interest", "establishment"], "place_id": "ChIJlcsoE3oVWBQRzKiHrlR_b34"}, {"name": "K Group", "formatted_address": "3A Abou Bakr El-Sedeek, El-Bostan, Heliopolis, Cairo Governorate, Egypt", "lat": 30.1051821, "lng": 31.3251103, "types": ["point_of_interest", "establishment"], "place_id": "ChIJOXHohZEVWBQRE1t1-jLRfmk"}, {"name": "صيدلية د.نجوى محروس", "formatted_address": "العقبه، El-Bostan, Heliopolis, Cairo Governorate, Egypt", "lat": 30.1043383, "lng": 31.3239115, "types": ["pharmacy", "health", "point_of_interest", "store", "establishment"], "place_id": "ChIJBYU5w5EVWBQRqmaAKpjMhDI"}, {"name": "Our Lady of Heliopolis Co-Cathedral", "formatted_address": "Nazih Khalifa crossroad، Al Ahram, Heliopolis, Cairo Governorate, Egypt", "lat": 30.0935707, "lng": 31.3251828, "types": ["church", "place_of_worship", "point_of_interest", "establishment"], "place_id": "ChIJJdgh-okVWBQR5TqTmKuQ0IM"}, {"name": "فاهم لخدمات الكمبيوتر", "formatted_address": "10 ش Rfaah Bek Rafaa, Mansheya El-Bakry, Heliopolis, Cairo Governorate, Egypt", "lat": 30.1033676, "lng": 31.3239365, "types": ["point_of_interest", "establishment"], "place_id": "ChIJMU-ZIY4VWBQRgkNsy1JZpjY"}, {"name": "اميه ترافيل سيرفيسز", "formatted_address": "9 أ Rfaah Bek Rafaa, El-Bostan, Heliopolis, Cairo Governorate, Egypt", "lat": 30.1033676, "lng": 31.3239365, "types": ["point_of_interest", "establishment"], "place_id": "ChIJMU-ZIY4VWBQRGjSyEkmMeJ0"}, {"name": "The Egyptian Museum", "formatted_address": "شارع ماريت باشا، ميدان التحرير، Egypt", "lat": 30.0475781, "lng": 31.23361389999999, "types": ["museum", "tourist_attraction", "point_of_interest", "establishment"], "place_id": "ChIJw741VYhBWBQRD2Z6OiulDVI"}, {"name": "مكتب سامي ميخائيل", "formatted_address": "4-3, Abd Al Aziz Al Beshri, El-Bostan, Heliopolis, Cairo Governorate, Egypt", "lat": 30.1029322, "lng": 31.3218213, "types": ["point_of_interest", "establishment"], "place_id": "ChIJOzBvt0kVWBQRKpdn3Wec6-c"}, {"name": "Loraadel", "formatted_address": "37 إسماعيل الفلكى، البستان، قسم مصر الجديدة،، Cairo Governorate, Egypt", "lat": 30.1050667, "lng": 31.3250021, "types": ["point_of_interest", "establishment"], "place_id": "ChIJv4baJxUVWBQRKdE3nrGKUzY"}, {"name": "Louvre", "formatted_address": "١٥٤ شارع جسر السويس امام سنترال مصر الجديدة التجنيد برج العليان, El-Bostan, Zeitoun, Cairo Governorate 11724, Egypt", "lat": 30.10543199999999, "lng": 31.3226293, "types": ["point_of_interest", "establishment"], "place_id": "ChIJ36D-wEkVWBQRHiPFvPiuUnY"}, {"name": "New Life Coworking Space", "formatted_address": "٨ اباظه, البستان, القاهرة 8 Abaza, البستان، St, Heliopolis, Cairo Governorate 11351, Egypt", "lat": 30.1039823, "lng": 31.3235827, "types": ["point_of_interest", "establishment"], "place_id": "ChIJQwAyoU8VWBQR0KbvHN1bFns"}, {"name": "Clarity", "formatted_address": "The Commercial & Residental building - B, 11 Abd Al Aziz Al Beshri, El-Bostan, Heliopolis, Cairo Governorate, Egypt", "lat": 30.104461, "lng": 31.3233334, "types": ["general_contractor", "point_of_interest", "establishment"], "place_id": "ChIJ84xIF4gVWBQRT4t2hpVrs0c"}, {"name": "دريا ترافيل", "formatted_address": "4 ش Othman Basha Ghaleb, El-Bostan, Heliopolis, Cairo Governorate, Egypt", "lat": 30.1024672, "lng": 31.3232298, "types": ["point_of_interest", "establishment"], "place_id": "ChIJn77LSY4VWBQRR3AtGguyN9w"}, {"name": "لوتس بيوتى سنتر", "formatted_address": "1 Al Sebaq, Al Matar, El Nozha, Cairo Governorate, Egypt", "lat": 30.1014156, "lng": 31.3243748, "types": ["point_of_interest", "establishment"], "place_id": "ChIJ1TX2Zo4VWBQROerKGWzGS-Q"}, {"name": "Venus", "formatted_address": "144شارع، جسر السويس، البستان، قسم مصر الجديدة، محافظة القاهرة‬،، البستان، قسم مصر الجديدة، محافظة القاهرة‬،، Egypt", "lat": 30.1042383, "lng": 31.3218683, "types": ["point_of_interest", "establishment"], "place_id": "ChIJu6MJDVMVWBQRe6LaNxUAag8"}, {"name": "Watani Radiology Center", "formatted_address": "10 Al Sebaq, El-Bostan, Heliopolis, Cairo Governorate, Egypt", "lat": 30.1023822, "lng": 31.3227684, "types": ["health", "point_of_interest", "establishment"], "place_id": "ChIJgQmbTI4VWBQROa2y1rntBXo"}, {"name": "Berfast", "formatted_address": "AZ Zaytoun Al Bahreyah, AZ Zaytoun, Cairo Governorate, Egypt", "lat": 30.1043815, "lng": 31.3213476, "types": ["point_of_interest", "establishment"], "place_id": "ChIJ8dMTIJAVWBQRNlDmgl1E1BI"}, {"name": "سوبر ماركت ابا", "formatted_address": "3 ب Rfaah Bek Rafaa, Mansheya El-Bakry, Heliopolis, Cairo Governorate, Egypt", "lat": 30.1028663, "lng": 31.324024, "types": ["point_of_interest", "establishment"], "place_id": "ChIJeSZqPY4VWBQR8yh8cdtXDGs"}, {"name": "Abo Rahma", "formatted_address": "AZ Zaytoun Al Bahreyah, AZ Zaytoun, Cairo Governorate, Egypt", "lat": 30.1049079, "lng": 31.3217706, "types": ["point_of_interest", "establishment"], "place_id": "ChIJI3THOpAVWBQRiWgkd09qMFQ"}, {"name": "مستشفى الامراض المتوطنة", "formatted_address": "البستان، مصر الجديدة،، Cairo Governorate, Egypt", "lat": 30.1035219, "lng": 31.3232473, "types": ["hospital", "health", "point_of_interest", "establishment"], "place_id": "ChIJnYWi9foVWBQRizTYF4P0Yg0"}, {"name": "Karam Rabie", "formatted_address": "37 Ismail El Falaky, El-Bostan, Heliopolis, Cairo Governorate, Egypt", "lat": 30.104916, "lng": 31.324787, "types": ["point_of_interest", "establishment"], "place_id": "ChIJdZV7z6oVWBQRCDU5PE4jS_4"}]