[{"name": "King Travel", "formatted_address": "بجوار حديقة الميريلاند, 3 أ علي ابو الفتوح من, El Hegaz St, Heliopolis, Cairo Governorate 11736, Egypt", "lat": 31.3253478, "types": ["travel_agency", "point_of_interest", "establishment"], "place_id": "ChIJh2OHa9cVWBQRpS3WF1PBykk"}, {"name": "Bab al-Futuh", "formatted_address": "Bab Al Foutoh, El-Gamaleya, El Gamaliya, Cairo Governorate, Egypt", "lat": 31.2634081, "types": ["tourist_attraction", "point_of_interest", "establishment"], "place_id": "ChIJI4VwkGI_WBQROZgXVyTN_IE"}, {"name": "Our Lady of Heliopolis Co-Cathedral", "formatted_address": "Nazih Khalifa crossroad، Al Ahram, Heliopolis, Cairo Governorate, Egypt", "lat": 31.3251828, "types": ["church", "place_of_worship", "point_of_interest", "establishment"], "place_id": "ChIJJdgh-okVWBQR5TqTmKuQ0IM"}, {"name": "Al Kholafaa Al Rashdeen Mosque", "formatted_address": "El Hegaz St, El-Bostan, Heliopolis, Cairo Governorate, Egypt", "lat": 31.3243996, "types": ["mosque", "place_of_worship", "point_of_interest", "establishment"], "place_id": "ChIJufJ9io4VWBQRRErdNLAMvpM"}, {"name": "Ittihadia Palace", "formatted_address": "Al Nadi، El-Montaza, Heliopolis, Cairo Governorate, Egypt", "lat": 31.3193929, "types": ["tourist_attraction", "premise", "point_of_interest", "establishment"], "place_id": "ChIJuftqUS8-WBQRtM7fDk0QcPk"}, {"name": "صيدليه د ايمان مغازي", "formatted_address": "18 شارع الحجاز مع علي ابو الفتوح ميدان المحكمه الجديده, Egypt", "lat": 31.3268928, "types": ["hospital", "health", "point_of_interest", "establishment"], "place_id": "ChIJkctmC5IVWBQRrkS1cEFqJso"}, {"name": "Bab El Nasr", "formatted_address": "Bab El-Nasr, El-Gamaleya, El Gamaliya, Cairo Governorate, Egypt", "lat": 31.2650414, "types": ["tourist_attraction", "point_of_interest", "establishment"], "place_id": "ChIJ2yl_V2I_WBQResgQVK-3o1s"}, {"name": "Baron Empain Palace", "formatted_address": "El-Orouba, El-Montaza, Heliopolis, Cairo Governorate 11757, Egypt", "lat": 31.3303332, "types": ["point_of_interest", "establishment"], "place_id": "ChIJ1_GM8iE-WBQRLNVi-RT7vDA"}, {"name": "Zuwayla Gate", "formatted_address": "Al Motaz Ldin Allah, El-Darb El-Ahmar, Cairo Governorate, Egypt", "lat": 31.2575191, "types": ["tourist_attraction", "general_contractor", "point_of_interest", "establishment"], "place_id": "ChIJN_TOs6ZAWBQR-t0c4vOwUdo"}, {"name": "صيدلية الأمل الجديدة", "formatted_address": "شارع الحجاز،مصر الجديدة،قسم، Ali Abou El-Fotouh, El-Bostan, Heliopolis, Cairo Governorate, Egypt", "lat": 31.3259686, "types": ["pharmacy", "health", "point_of_interest", "store", "establishment"], "place_id": "ChIJc9RC5I0VWBQRjAJw6WGuc58"}, {"name": "Bon Voyage", "formatted_address": "16 Adly, Al Fawalah, Abdeen, Cairo Governorate, Egypt", "lat": 31.244439, "types": ["tourist_attraction", "point_of_interest", "establishment"], "place_id": "ChIJJZ3TEL5AWBQRc-PhG_sO-S0"}, {"name": "Physics World", "formatted_address": "35 Abaza, El-Bostan, Heliopolis, Cairo Governorate, Egypt", "lat": 31.3263032, "types": ["point_of_interest", "establishment"], "place_id": "ChIJsShUBZIVWBQRLSVdd_b2akM"}, {"name": "Samer Abd Elazez Atya", "formatted_address": "138 El Hegaz St, El-Bostan, Heliopolis, Cairo Governorate, Egypt", "lat": 31.3270433, "types": ["point_of_interest", "establishment"], "place_id": "ChIJe62YdJIVWBQR39GU9cp3y7Q"}, {"name": "Zogmar Bikes", "formatted_address": "138 El Hegaz St, El-Bostan, Heliopolis, Cairo Governorate, Egypt", "lat": 31.3264334, "types": ["car_repair", "point_of_interest", "establishment"], "place_id": "ChIJ79AkWswVWBQRG6zG6duGJjs"}, {"name": "Salah Al-Din Al-Ayoubi Castle, Salah Salem Street, Cairo", "formatted_address": "Salah Salem St, Al Abageyah, El-Khalifa, Cairo Governorate, Egypt", "lat": 31.2594688, "types": ["point_of_interest", "establishment"], "place_id": "ChIJY-3CkKxAWBQRby736eSW2y8"}, {"name": "Dynamic", "formatted_address": "138 El Hegaz St, El-Bostan, Heliopolis, Cairo Governorate, Egypt", "lat": 31.3267174, "types": ["lodging", "point_of_interest", "establishment"], "place_id": "ChIJj0HZzeMVWBQRhAd8gRqW9pU"}, {"name": "Al-Azhar Mosque", "formatted_address": "El-Darb El-Ahmar, Cairo Governorate, Egypt", "lat": 31.2626851, "types": ["mosque", "tourist_attraction", "place_of_worship", "point_of_interest", "establishment"], "place_id": "ChIJ9SH986JAWBQR6FIeS8dSZ2c"}, {"name": "Café Marshillo", "formatted_address": "138 شارع الحجاز، البستان، قسم مصر الجديدة، محافظة القاهرة‬،، Egypt", "lat": 31.3265814, "types": ["restaurant", "food", "point_of_interest", "establishment"], "place_id": "ChIJAYjQpaQVWBQR39VumjozWkM"}, {"name": "Eagle Car Rental", "formatted_address": "12 شارع الحجاز،، Al Mahkma, Heliopolis, Cairo Governorate 11737, Egypt", "lat": 31.326536, "types": ["car_rental", "point_of_interest", "establishment"], "place_id": "ChIJ2fpt8Y0VWBQR-PxLlYqgTKY"}, {"name": "مكتب بريد زهراء عين شمس", "formatted_address": "27ش، Abou El-Fotouh Abd Allah, Ain Shams Sharkeya, Ein Shams, Cairo Governorate, Egypt", "lat": 31.3401028, "types": ["post_office", "finance", "point_of_interest", "establishment"], "place_id": "ChIJnzak2TIUWBQR7G9ntoRkTUM"}, {"name": "هوليداي هوم", "formatted_address": "قسم مصر الجديدة, 63 El Hegaz St, El-Bostan, Heliopolis, Cairo Governorate 11351, Egypt", "lat": 31.3275635, "types": ["lodging", "point_of_interest", "establishment"], "place_id": "ChIJD__keZIVWBQRaRwfB2gBVVo"}, {"name": "Great Sphinx of Giza", "formatted_address": "Al Giza Desert, Giza Governorate, Egypt", "lat": 31.1375674, "types": ["tourist_attraction", "point_of_interest", "establishment"], "place_id": "ChIJeamuo2JPWBQRqb1mQKbw08k"}, {"name": "St. Mark Coptic Orthodox Church Cleopatra", "formatted_address": "35 كيلوباترا، الماظة، قسم مصر الجديدة،، Cairo Governorate, Egypt", "lat": 31.3296246, "types": ["church", "place_of_worship", "point_of_interest", "establishment"], "place_id": "ChIJH3kNmooVWBQRfL4z5mf-KXU"}, {"name": "Spine care center", "formatted_address": "11 شارع احمد السكندرى تقاطع، Abdallah Al Nadim, Heliopolis, Cairo Governorate, Egypt", "lat": 31.3248699, "types": ["doctor", "health", "point_of_interest", "establishment"], "place_id": "ChIJ0wt8MeYVWBQRCrUC5gOo-aA"}, {"name": "Nansy", "formatted_address": "138 El Hegaz St, El-Bostan, Heliopolis, Cairo Governorate, Egypt", "lat": 31.3258816, "types": ["book_store", "point_of_interest", "store", "establishment"], "place_id": "ChIJMbkp_I0VWBQRaIRJniwpfTo"}, {"name": "Iris Optics Heliopolis", "formatted_address": "14 El Hegaz St, El-Montaza, Heliopolis, Cairo Governorate, Egypt", "lat": 31.3266072, "types": ["point_of_interest", "store", "establishment"], "place_id": "ChIJJ1uiVUMVWBQR8yf0GkBfJ18"}, {"name": "الدكتور محمد حامد", "formatted_address": "١٤ شارع الحجاز ميدان المحكمة, 11351, Egypt", "lat": 31.3269584, "types": ["health", "point_of_interest", "establishment"], "place_id": "ChIJw77wOr8VWBQRAAqMZFa-13o"}, {"name": "Nshape ارض الجولف", "formatted_address": "Asmaa Fahmi, Al Golf, Nasr City, Cairo Governorate, Egypt", "lat": 31.3382582, "types": ["point_of_interest", "establishment"], "place_id": "ChIJK24uUhc-WBQROSbDAGuBic8"}, {"name": "Beauty avenue clinic", "formatted_address": "138 El Hegaz St, El-Bostan, Heliopolis, Cairo Governorate, Egypt", "lat": 31.3264683, "types": ["health", "point_of_interest", "establishment"], "place_id": "ChIJT08sPH4VWBQR-q2qOkcH0F4"}, {"name": "Autono Hamza", "formatted_address": "138 El Hegaz St, El-Bostan, Heliopolis, Cairo Governorate, Egypt", "lat": 31.3258816, "types": ["car_dealer", "point_of_interest", "store", "establishment"], "place_id": "ChIJawaI_o0VWBQRZ-BVnWhKxJo"}, {"name": "أوتومبيل الحجاز", "formatted_address": "58 El Hegaz St, El-Bostan, Heliopolis, Cairo Governorate, Egypt", "lat": 31.3268646, "types": ["car_dealer", "point_of_interest", "store", "establishment"], "place_id": "ChIJ_-1s7I0VWBQRfjBQLeXsqsA"}, {"name": "ValuesTec", "formatted_address": "12 El Hegaz St, El-Bostan, Heliopolis, Cairo Governorate, Egypt", "lat": 31.326536, "types": ["point_of_interest", "establishment"], "place_id": "ChIJ1U-DRcoVWBQRf92dXw6wnqg"}, {"name": "أسواق الشريف", "formatted_address": "59 El Hegaz St, El-Bostan, Heliopolis, Cairo Governorate, Egypt", "lat": 31.326606, "types": ["home_goods_store", "point_of_interest", "store", "establishment"], "place_id": "ChIJueVl6Y0VWBQRLdVJ87JKADE"}, {"name": "Radisson Blu Hotel, Cairo Heliopolis", "formatted_address": "Abdel Hamid Badawi St Heliopolis, Cairo Governorate 11787, Egypt", "lat": 31.3753121, "types": ["lodging", "point_of_interest", "establishment"], "place_id": "ChIJQZJ8fWUWWBQRAUPO9I6SxPg"}, {"name": "El Hawawshy El Asly", "formatted_address": "63 El Hegaz St, El-Bostan, Heliopolis, Cairo Governorate, Egypt", "lat": 31.3271029, "types": ["restaurant", "food", "point_of_interest", "establishment"], "place_id": "ChIJ06TYwusVWBQRERwG2nFRCvs"}, {"name": "Heliopolis Family Court", "formatted_address": "58 El Hegaz St, El-Nozha, Heliopolis, Cairo Governorate, Egypt", "lat": 31.3297672, "types": ["courthouse", "local_government_office", "point_of_interest", "establishment"], "place_id": "ChIJNxzB6pIVWBQRQx6kT15XA74"}, {"name": "Il Pennello Ceramic Café & Restaurant", "formatted_address": "Omar Ibn El-Khattab, El-Bostan, Heliopolis, Cairo Governorate, Egypt", "lat": 31.33329, "types": ["cafe", "restaurant", "food", "point_of_interest", "establishment"], "place_id": "ChIJA9aGkfIVWBQR6C-ilXdzmvM"}, {"name": "British Council", "formatted_address": "4 Minya, El-Bostan, Heliopolis, Cairo Governorate, Egypt", "lat": 31.3236016, "types": ["point_of_interest", "establishment"], "place_id": "ChIJz8iNp4kVWBQRdB9ba3Xvh0M"}, {"name": "Skin Life Clinic", "formatted_address": "El Hegaz St, El-Bostan, Heliopolis, Cairo Governorate, Egypt", "lat": 31.3264883, "types": ["health", "point_of_interest", "establishment"], "place_id": "ChIJoUXT7o0VWBQRQJIS1X3CdeM"}, {"name": "(Heliopolis Public library)", "formatted_address": "Beirut, Almazah, Heliopolis, Cairo Governorate, Egypt", "lat": 31.3328428, "types": ["library", "point_of_interest", "establishment"], "place_id": "ChIJd3h9YvUVWBQR2Oi9DLQTI8E"}, {"name": "دار الرويعى للمعادن", "formatted_address": "ش ابو الفتوح، عبده صابر، Ein Shams, Cairo Governorate, Egypt", "lat": 31.3452061, "types": ["hardware_store", "point_of_interest", "store", "establishment"], "place_id": "ChIJ37TWJS0UWBQRTe6uLEEwFg4"}, {"name": "سوبر ماركت السعادة", "formatted_address": "12 El Hegaz St, Al Matar, El Nozha, Cairo Governorate, Egypt", "lat": 31.326536, "types": ["supermarket", "grocery_or_supermarket", "food", "point_of_interest", "store", "establishment"], "place_id": "ChIJkWv09o0VWBQR3FfCkjqp_bA"}, {"name": "Regency Café & Restaurant", "formatted_address": "63 El Hegaz St, El-Nozha, قسم النزهة،، Cairo Governorate, Egypt", "lat": 31.3269645, "types": ["cafe", "restaurant", "food", "point_of_interest", "establishment"], "place_id": "ChIJvZoO8Y0VWBQR-Wu4O6hswuE"}, {"name": "devgist", "formatted_address": "12 El Hegaz St, El-Bostan, Heliopolis, Cairo Governorate, Egypt", "lat": 31.326536, "types": ["point_of_interest", "establishment"], "place_id": "ChIJvyFoixcVWBQRd5kcvD1EID8"}, {"name": "أبو الفتوح", "formatted_address": "130 ش المطراوى، Shagret Mariem, El Matareya, Cairo Governorate, Egypt", "lat": 31.3082077, "types": ["point_of_interest", "store", "establishment"], "place_id": "ChIJB6FupwkVWBQRUG5svFWvd3U"}, {"name": "Hotel Concorde El Salam Cairo By Royal Tulip", "formatted_address": "69 Abd El-Hameed Badawi, St، El Nozha, Cairo Governorate, Egypt", "lat": 31.3480627, "types": ["lodging", "point_of_interest", "establishment"], "place_id": "ChIJ3b5I-fUVWBQRVG_oX-wQmZE"}, {"name": "Church of the Great Martyr Saint George and Anba Ebram - كنيسة الشهيد العظيم مارجرجس و الأنبا ابرآم", "formatted_address": "54 Abd El-Aziz Fahmy, Al Matar, El Nozha, Cairo Governorate, Egypt", "lat": 31.3392792, "types": ["church", "place_of_worship", "point_of_interest", "establishment"], "place_id": "ChIJvzrXsekVWBQRye4OpOsJnNM"}, {"name": "Esparanza Educational Pre-School", "formatted_address": "5 متفرع من ش بيروت، El-Bostan, Heliopolis, Cairo Governorate, Egypt", "lat": 31.3256663, "types": ["school", "point_of_interest", "establishment"], "place_id": "ChIJ2cDGBSA-WBQRL3-vsLH7Hnc"}, {"name": "Heliopolis Towers Hotel", "formatted_address": "El Shaheed Sayed Zakaria, Sheraton Al Matar, El Nozha, Cairo Governorate 11736, Egypt", "lat": 31.3661798, "types": ["lodging", "point_of_interest", "establishment"], "place_id": "ChIJZ9p3820WWBQRmZh2M_MSzOQ"}, {"name": "Al Amira Center - مركز الاميرة", "formatted_address": "12 El Hegaz St, El-Bostan, Heliopolis, Cairo Governorate 11351, Egypt", "lat": 31.3264442, "types": ["point_of_interest", "establishment"], "place_id": "ChIJPUkCDjUVWBQRLaOtBFzSUPc"}, {"name": "رينو ابو الفتوح م. نصر Renault Abou Elfetouh", "formatted_address": "شارع Al Khalifa Al Zaher, Al Hay as Sabea, Nasr City, Cairo Governorate, Egypt", "lat": 31.3261025, "types": ["car_repair", "point_of_interest", "store", "establishment"], "place_id": "ChIJOz911PM-WBQR2d6HZRbQYbg"}, {"name": "يلا عجلة", "formatted_address": "El-Bostan, Heliopolis, Cairo Governorate, Egypt", "lat": 31.3253464, "types": ["point_of_interest", "establishment"], "place_id": "ChIJBcQJ8KcVWBQR-mxX2GG3OFs"}, {"name": "Sayed El Sharqawy Restaurant", "formatted_address": "شارع Abou El-Fotouh Abd Allah, ،عين شمس ،قسم، Ein Shams, Cairo Governorate, Egypt", "lat": 31.3389957, "types": ["restaurant", "food", "point_of_interest", "establishment"], "place_id": "ChIJDVvpPMZAWBQRNrniaJLKiyc"}, {"name": "TiE HOUSE", "formatted_address": "Merryland Park, 26 El Hegaz St, El-Bostan, Heliopolis, Cairo Governorate, Egypt", "lat": 31.3231775, "types": ["shoe_store", "point_of_interest", "clothing_store", "store", "establishment"], "place_id": "ChIJi86qod5GWBQRcozRUEuCJp0"}, {"name": "Drinkies", "formatted_address": "El-Bostan, Heliopolis, Cairo Governorate, Egypt", "lat": 31.32610949999999, "types": ["liquor_store", "point_of_interest", "store", "establishment"], "place_id": "ChIJx0X82KEVWBQR8L4LHKWJID0"}, {"name": "محمد أبو الفتوح سعد", "formatted_address": "شارع El-Khalifa El-Maamoun, Mansheya El-Bakry, Heliopolis, Cairo Governorate, Egypt", "lat": 31.31034379999999, "types": ["doctor", "health", "point_of_interest", "establishment"], "place_id": "ChIJo2dw4iw-WBQRfIIIJvRVZ74"}, {"name": "Hedeya Heliopolis Branch", "formatted_address": "25 El-Horreya St. - off, El-Nozha, Cairo Governorate 11757, Egypt", "lat": 31.3394971, "types": ["point_of_interest", "clothing_store", "store", "establishment"], "place_id": "ChIJzXYzCrE_WBQRFRjWzFCKNaE"}, {"name": "مكتب محمد أبو الفتوح", "formatted_address": "Al Manteqah Al Oula, Nasr City, Cairo Governorate, Egypt", "lat": 31.33447589999999, "types": ["lawyer", "point_of_interest", "establishment"], "place_id": "ChIJaclr9Gg-WBQR188gCE36-ec"}, {"name": "El Khateeb Dental Clinc", "formatted_address": "El Hegaz St, El-Bostan, Heliopolis, Cairo Governorate, Egypt", "lat": 31.326485, "types": ["health", "point_of_interest", "establishment"], "place_id": "ChIJt6z68o0VWBQRjtqsymArT9g"}, {"name": "حاتى الحسين", "formatted_address": "ش أبو الفتوح،عين شمس،قسم متفرع من، Ahmed Oraby, Ain Shams Sharkeya, Ein Shams, Egypt", "lat": 31.3462359, "types": ["restaurant", "food", "point_of_interest", "establishment"], "place_id": "ChIJjd9EwywUWBQRdJBWftewTjM"}]