[{"name": "Air Force Museum", "formatted_address": "داخل مطار الماظة، Sheraton Al Matar, El Nozha, Cairo Governorate, Egypt", "lat": 31.3512283, "types": ["museum", "point_of_interest", "establishment"], "place_id": "ChIJ3cxcs-MVWBQRtEbyyE8PXCo"}, {"name": "متحف القوات الجوية المصرية", "formatted_address": "Sheraton Al Matar, El Nozha, Cairo Governorate, Egypt", "lat": 31.3526919, "types": ["museum", "tourist_attraction", "point_of_interest", "establishment"], "place_id": "ChIJnxbZwOIVWBQRb_Jw3qPqz7E"}, {"name": "Almaza Airbase", "formatted_address": "شيراتون المطار، قسم النزهة، محافظة القاهرة‬،، شيراتون المطار، قسم النزهة، محافظة القاهرة‬،، Egypt", "lat": 31.351505, "types": ["airport", "point_of_interest", "establishment"], "place_id": "ChIJAdyryYAVWBQR6AYdw4vuDxc"}, {"name": "فندق مجمع النسور", "formatted_address": "داخل مطار الماظة، Sheraton Al Matar, El Nozha, Cairo Governorate, Egypt", "lat": 31.3677317, "types": ["lodging", "point_of_interest", "establishment"], "place_id": "ChIJQVkHPhsWWBQRr2HCIcv5kO8"}, {"name": "دار النسور", "formatted_address": "داخل مطار الماظة، Sheraton Al Matar, El Nozha, Cairo Governorate, Egypt", "lat": 31.366492, "types": ["point_of_interest", "establishment"], "place_id": "ChIJPS3NJRsWWBQR03skr9BgQak"}, {"name": "City Centre Almaza", "formatted_address": "Passage Inside Almaza Airport, Sheraton Al Matar, El Nozha, Cairo Governorate, Egypt", "lat": 31.3651812, "types": ["shopping_mall", "point_of_interest", "establishment"], "place_id": "ChIJae0gF_g9WBQRz6pWyx0wl7U"}, {"name": "Our Lady of Heliopolis Co-Cathedral", "formatted_address": "Nazih Khalifa crossroad، Al Ahram, Heliopolis, Cairo Governorate, Egypt", "lat": 31.3251828, "types": ["church", "place_of_worship", "point_of_interest", "establishment"], "place_id": "ChIJJdgh-okVWBQR5TqTmKuQ0IM"}, {"name": "Church of the Great Martyr George - Almaza", "formatted_address": "Labib Gergis, Almazah, Heliopolis, Cairo Governorate, Egypt", "lat": 31.3504355, "types": ["church", "place_of_worship", "point_of_interest", "establishment"], "place_id": "ChIJBfJ7bv8VWBQRjhG1RyNygTg"}, {"name": "Almaza Superjet Stop", "formatted_address": "ممر داخل حديقة الاسرة، Almazah, Heliopolis, Cairo Governorate, Egypt", "lat": 31.3474806, "types": ["food", "point_of_interest", "store", "establishment"], "place_id": "ChIJcx86JfkVWBQR1xUwclV12To"}, {"name": "Go Bus Almaza", "formatted_address": "11 Hussein Kamel, Almazah, Heliopolis, Cairo Governorate, Egypt", "lat": 31.3536196, "types": ["travel_agency", "point_of_interest", "establishment"], "place_id": "ChIJEzJvAgA-WBQRZfuPE0O0dJA"}, {"name": "Porto Heliopolis", "formatted_address": "Almazah, Heliopolis, Cairo Governorate, Egypt", "lat": 31.348709, "types": ["lodging", "point_of_interest", "establishment"], "place_id": "ChIJR5FCXgE-WBQR471eyuZuvGw"}, {"name": "Hilton Cairo Heliopolis", "formatted_address": "El-Orouba, Sheraton Al Matar, El Nozha, Cairo Governorate, Egypt", "lat": 31.3646213, "types": ["lodging", "point_of_interest", "establishment"], "place_id": "ChIJUYFpLCELRRQRzCxbUHFt6Vs"}, {"name": "the Community Egypt - tC Egypt", "formatted_address": "in front of Egypt Air Hospital، ١٨ شارع الشهيد صبحي نصر، ألماظة- مصر الجديدة - أمام مستشفى مصر للطيران 18 El Shaheed Sobhy Nasr, Al Maza، Almazah, Heliopolis, Egypt", "lat": 31.3451647, "types": ["point_of_interest", "establishment"], "place_id": "ChIJm913ZfkVWBQR7oyf09bOQm4"}, {"name": "Almaza Avenue Mall", "formatted_address": "كوبري اليرغني الماظة, كوبرى الماظة، 159 مصطفى طلبه، الماظة، مصر الجديدة، محافظة القاهرة‬،، الماظة، قسم مصر الجديدة، محافظة القاهرة‬،،, الماظة، قسم النزهة، محافظة القاهرة‬،, Egypt", "lat": 31.3470089, "types": ["shopping_mall", "point_of_interest", "establishment"], "place_id": "ChIJB-euKrQVWBQRKjUVjfGfNKs"}, {"name": "Dar Al Eshara", "formatted_address": "Masaken Al Mohandesin, Nasr City, Cairo Governorate, Egypt", "lat": 31.3488, "types": ["point_of_interest", "establishment"], "place_id": "ChIJLyhTqQY-WBQRc1aMkVsnYv8"}, {"name": "Bon Voyage", "formatted_address": "16 Adly, Al Fawalah, Abdeen, Cairo Governorate, Egypt", "lat": 31.244439, "types": ["tourist_attraction", "point_of_interest", "establishment"], "place_id": "ChIJJZ3TEL5AWBQRc-PhG_sO-S0"}, {"name": "Eagle's Club", "formatted_address": "داخل مطار الماظة، Sheraton Al Matar, El Nozha, Cairo Governorate, Egypt", "lat": 31.3676721, "types": ["gym", "health", "point_of_interest", "establishment"], "place_id": "ChIJC0Qj5RoWWBQRtq75mcf1F-8"}, {"name": "مركز زايد", "formatted_address": "داخل مطار الماظة، Sheraton Al Matar, El Nozha, Cairo Governorate, Egypt", "lat": 31.3661482, "types": ["hospital", "health", "point_of_interest", "establishment"], "place_id": "ChIJS0egLRsWWBQRwvAvT7xwKbM"}, {"name": "Aerobics", "formatted_address": "داخل مطار الماظة،, Sheraton Al Matar, El Nozha, Cairo Governorate, Egypt", "lat": 31.3675847, "types": ["gym", "health", "point_of_interest", "establishment"], "place_id": "ChIJq40i-u4XWBQRa6tUyhSvpfA"}, {"name": "مؤسسة الزهراوان", "formatted_address": "4 Al Shahid Moustafa Tabalah, Almazah, Heliopolis, Cairo Governorate, Egypt", "lat": 31.34515399999999, "types": ["point_of_interest", "establishment"], "place_id": "ChIJBWy_rvkVWBQRmw2XrIBI0nk"}, {"name": "فندق دار المدفعيه", "formatted_address": "El-Thawra St, Masaken Al Mohandesin, Heliopolis, Cairo Governorate, Egypt", "lat": 31.35416739999999, "types": ["lodging", "point_of_interest", "establishment"], "place_id": "ChIJjUF1Av49WBQRxA4a0lsk4nU"}, {"name": "Heliopolis Towers Hotel", "formatted_address": "El Shaheed Sayed Zakaria, Sheraton Al Matar, El Nozha, Cairo Governorate 11736, Egypt", "lat": 31.3661798, "types": ["lodging", "point_of_interest", "establishment"], "place_id": "ChIJZ9p3820WWBQRmZh2M_MSzOQ"}, {"name": "Jet Bird", "formatted_address": "داخل مطار الماظة، Sheraton Al Matar, El Nozha, Cairo Governorate, Egypt", "lat": 31.3756715, "types": ["point_of_interest", "establishment"], "place_id": "ChIJA2DlaRsWWBQRv9BF5ceNQmE"}, {"name": "NBK بنك الكويت الوطني", "formatted_address": "حى الملتقى العربى بألماظة، قسم النزهة، القاهرة, Passage Inside Almaza Airport, Sheraton Al Matar, El Nozha, Cairo Governorate, Egypt", "lat": 31.3660085, "types": ["bank", "finance", "point_of_interest", "establishment"], "place_id": "ChIJJREwPzk9WBQR3CM8FzqE4yI"}, {"name": "Tivoli Dome", "formatted_address": "Omar Ibn El-Khattab, Almazah, Heliopolis, Cairo Governorate, Egypt", "lat": 31.3479517, "types": ["food", "point_of_interest", "establishment"], "place_id": "ChIJsSxOPgI-WBQRz6H2FJMg2uE"}, {"name": "Almaza Bus Station", "formatted_address": "El-Horeya, Almazah, Heliopolis, Cairo Governorate, Egypt", "lat": 31.3482941, "types": ["point_of_interest", "establishment"], "place_id": "ChIJI5280_4VWBQRjbU_u2fj52Q"}, {"name": "The Bunker", "formatted_address": "Almazah, Heliopolis, Cairo Governorate, Egypt", "lat": 31.3464799, "types": ["point_of_interest", "establishment"], "place_id": "ChIJKdVCWIAVWBQRKWsBCKGl_jM"}, {"name": "Emarat Dobat Almaza", "formatted_address": "كوبري الجيش المصري شارع الثورة، Suez Rd, Cairo Governorate, Egypt", "lat": 31.3781607, "types": ["point_of_interest", "establishment"], "place_id": "ChIJgf9kDCAWWBQRi4JaojsihaQ"}, {"name": "A|X Il Cairo Almaza", "formatted_address": "Passage Inside Almaza Airport, Sheraton Al Matar, El Nozha, Cairo Governorate, Egypt", "lat": 31.3657082, "types": ["point_of_interest", "clothing_store", "store", "establishment"], "place_id": "ChIJpRWD9AhBWBQRfdtu_jj0RCU"}, {"name": "St. Mark Coptic Orthodox Church Cleopatra", "formatted_address": "35 كيلوباترا، الماظة، قسم مصر الجديدة،، Cairo Governorate, Egypt", "lat": 31.3296246, "types": ["church", "place_of_worship", "point_of_interest", "establishment"], "place_id": "ChIJH3kNmooVWBQRfL4z5mf-KXU"}, {"name": "Almaza Avenue", "formatted_address": "Sheraton Al Matar, El Nozha, Cairo Governorate, Egypt", "lat": 31.3690319, "types": ["general_contractor", "point_of_interest", "establishment"], "place_id": "ChIJY98FhRsWWBQRYYYnJl4EBNA"}, {"name": "Escape Room", "formatted_address": "104 Omar Ibn El-Khattab, Almazah, Heliopolis, Cairo Governorate, Egypt", "lat": 31.3469713, "types": ["point_of_interest", "establishment"], "place_id": "ChIJwQ24dAI-WBQREWgtXDqCbRM"}, {"name": "Del vento sushi", "formatted_address": "داخل مطار الماظة،, Sheraton Al Matar, El Nozha, Cairo Governorate, Egypt", "lat": 31.3484925, "types": ["restaurant", "food", "point_of_interest", "establishment"], "place_id": "ChIJx2I1QD4VWBQRKurYvAfb-7I"}, {"name": "وادي النيل للرعاية والخدمات الطبية", "formatted_address": "Almazah, Heliopolis, Cairo Governorate, Egypt", "lat": 31.3464152, "types": ["point_of_interest", "establishment"], "place_id": "ChIJad83EvkVWBQRZRliYdNSb14"}, {"name": "Egypt Air Hospital", "formatted_address": "Sheraton Al Matar, El Nozha, Cairo Governorate, Egypt", "lat": 31.3488849, "types": ["hospital", "health", "point_of_interest", "establishment"], "place_id": "ChIJeS4JAvwVWBQRpL3MOlh6Qrg"}, {"name": "Air Arabia", "formatted_address": "florida towers sheraton, Sheraton Al Matar, El Nozha, Cairo Governorate, Egypt", "lat": 31.370389, "types": ["travel_agency", "point_of_interest", "establishment"], "place_id": "ChIJmVe2b-oXWBQR2cXq4BR1S0U"}, {"name": "Gravity Code City Center Almaza", "formatted_address": "Sheraton Al Matar, El Nozha, Cairo Governorate, Egypt", "lat": 31.3645679, "types": ["point_of_interest", "establishment"], "place_id": "ChIJJYK9u7Y9WBQRKq-7C6hgjlI"}, {"name": "Cairo International Airport", "formatted_address": "Oruba، Road، El Nozha, Cairo Governorate, Egypt", "lat": 31.3997904, "types": ["airport", "point_of_interest", "establishment"], "place_id": "ChIJQU-oLggXWBQRhhPiUSGvZeA"}, {"name": "East Delta Travel", "formatted_address": "ميدان الماظة، Almazah, Heliopolis, Cairo Governorate, Egypt", "lat": 31.3484439, "types": ["point_of_interest", "establishment"], "place_id": "ChIJZWGdagI-WBQRFbMLQDBvknA"}, {"name": "Mori Sushi", "formatted_address": "Tivoli Dome, 70 Almaza Square, Heliopolis, Cairo, Egypt", "lat": 31.3480622, "types": ["restaurant", "food", "point_of_interest", "establishment"], "place_id": "ChIJi39xFwI-WBQRjNDHsNFsCak"}, {"name": "Citystars Heliopolis", "formatted_address": "Citystars, Cairo Governorate 11771, Egypt", "lat": 31.3458082, "types": ["shopping_mall", "point_of_interest", "establishment"], "place_id": "ChIJo0ecE_gVWBQRGGrouhZFdME"}, {"name": "Diwan Bookstore", "formatted_address": "105 Abou Bakr El-Sedeek, Almazah, Heliopolis, Cairo Governorate, Egypt", "lat": 31.3412005, "types": ["book_store", "point_of_interest", "store", "establishment"], "place_id": "ChIJkTmV7PAVWBQRthTVz3MR8nM"}, {"name": "كبدة ومخ شرقاوى الماظة مصرالجديدة", "formatted_address": "٦شارع عزت محمدسليم، الماظة. مصر الجديدة،بجوار جوباص وبوابة التاكس الطاير.ودارالاشارة وشارع، عزت محمد سليم، النزهة، محافظة القاهرة‬ 11311، مصرالجديدة القاهرة، 11311الحجاز، عزت محمد سليم، القاهرة مصرالجديدة، Egypt", "lat": 31.3533279, "types": ["restaurant", "food", "point_of_interest", "establishment"], "place_id": "ChIJVVUJGwA-WBQR2Em1P5GvKh0"}, {"name": "TiE HOUSE", "formatted_address": "Passage Inside Almaza Airport, Sheraton Al Matar, El Nozha, Cairo Governorate 11775, Egypt", "lat": 31.364764, "types": ["point_of_interest", "clothing_store", "store", "establishment"], "place_id": "ChIJGU54N0w9WBQRItsamQDQjMw"}, {"name": "Lemon Spaces sheraton Heliopolis", "formatted_address": "Building # 19، El-Safa, Sheraton Al Matar, El Nozha, Cairo Governorate, Egypt", "lat": 31.3667492, "types": ["lodging", "point_of_interest", "establishment"], "place_id": "ChIJ0dUH_3oXWBQRT1ZYgsJShvE"}, {"name": "Health Bureau - Almaza", "formatted_address": "38 Fathi Al Ashlan, Almazah, Heliopolis, Cairo Governorate, Egypt", "lat": 31.3523539, "types": ["point_of_interest", "establishment"], "place_id": "ChIJ6TGL8QA-WBQRQDet_g_W-Ig"}, {"name": "Sharei’a Association Hospital For Premature Infants & Newborns", "formatted_address": "ش الشهيد اسماعيل موسى، Almazah, Heliopolis, Cairo Governorate, Egypt", "lat": 31.3545047, "types": ["hospital", "health", "point_of_interest", "establishment"], "place_id": "ChIJA_GC0_89WBQR5tsT1zXMxTs"}, {"name": "Murano Cafe مورانو كافيه", "formatted_address": "Hussein Kamel, Almazah, Heliopolis, Cairo Governorate, Egypt", "lat": 31.3512077, "types": ["cafe", "food", "point_of_interest", "establishment"], "place_id": "ChIJwcdOkCsVWBQR_lYu52cYiYQ"}, {"name": "Burger King - Tivoli Dome Heliopolis", "formatted_address": "Tivoli Dome, Omar Ibn El Khattab St، Almazah, Heliopolis, Cairo Governorate, Egypt", "lat": 31.3478102, "types": ["restaurant", "food", "point_of_interest", "establishment"], "place_id": "ChIJ8asB1I8_WBQR-CVqCM1YprU"}, {"name": "(Heliopolis Public library)", "formatted_address": "Beirut, Almazah, Heliopolis, Cairo Governorate, Egypt", "lat": 31.3328428, "types": ["library", "point_of_interest", "establishment"], "place_id": "ChIJd3h9YvUVWBQR2Oi9DLQTI8E"}, {"name": "Crave City Center Almaza", "formatted_address": "Passage Inside Almaza Airport, Sheraton Al Matar, El Nozha, Cairo Governorate, Egypt", "lat": 31.3729179, "types": ["restaurant", "food", "point_of_interest", "establishment"], "place_id": "ChIJM59rINgXWBQRxG7zZ6Uf5uQ"}, {"name": "Ahlan VIP Service - خدمة اهلا مطار القاهرة", "formatted_address": "طريق المطار، Sheraton Al Matar, El Nozha, Cairo Governorate, Egypt", "lat": 31.37264059999999, "types": ["airport", "point_of_interest", "establishment"], "place_id": "ChIJub-Qux0XWBQRI4ImWBLvd7w"}, {"name": "IDP Education & IELTS Testing - Cairo", "formatted_address": "31 Omar Bekir St off Othman Ibn Afan St, Othman Ibn Affan, Nozha, Cairo Governorate 11361, Egypt", "lat": 31.348553, "types": ["point_of_interest", "establishment"], "place_id": "ChIJYWJmM-EVWBQRsRn2yOGljFo"}, {"name": "Aloush Heliopolis", "formatted_address": "الماظة ، مصر الجديدة ، عمارة 135, Heliopolis, Cairo Governorate, Egypt", "lat": 31.347398, "types": ["cafe", "restaurant", "food", "point_of_interest", "establishment"], "place_id": "ChIJM7jmwwM-WBQRCv7xsNzKuvA"}, {"name": "LAKMA", "formatted_address": "83 El-Horeya, Almazah, Heliopolis, Cairo Governorate, Egypt", "lat": 31.347945, "types": ["restaurant", "food", "point_of_interest", "establishment"], "place_id": "ChIJ16evyfgVWBQRlGhsJ8Y_xm8"}, {"name": "ZARA Home", "formatted_address": "Passage Inside Almaza Airport, Sheraton Al Matar, El Nozha, Cairo Governorate, Egypt", "lat": 31.36471199999999, "types": ["home_goods_store", "point_of_interest", "store", "establishment"], "place_id": "ChIJed5nNpM9WBQRnEt3ZNrQijA"}, {"name": "Eng. Military Auth. House", "formatted_address": "Mansheya El-Bakry, Heliopolis, Cairo Governorate, Egypt", "lat": 31.30596509999999, "types": ["lodging", "point_of_interest", "establishment"], "place_id": "ChIJOQqUcss_WBQRlT7AQB0UXK8"}, {"name": "Magic planet", "formatted_address": "Sheraton Al Matar, El Nozha, Cairo Governorate, Egypt", "lat": 31.3646602, "types": ["point_of_interest", "establishment"], "place_id": "ChIJmXK8yjI9WBQR1X3BzHRHL_0"}, {"name": "جاردينيا", "formatted_address": "Suez Rd, Sheraton Al Matar, El Nozha, Cairo Governorate, Egypt", "lat": 31.40276, "types": ["point_of_interest", "establishment"], "place_id": "ChIJOcPjhjUXWBQRIVunqICmf-E"}, {"name": "لكمة", "formatted_address": "83 الحرية، الماظة،، Heliopolis, Cairo Governorate, Egypt", "lat": 31.3481123, "types": ["restaurant", "food", "point_of_interest", "establishment"], "place_id": "ChIJ-VoKcb8VWBQRs-9g1QHiwv0"}]