[{"name": "Rabea Ewais Abdel Maaboud Law Office", "formatted_address": "Kafr Al Olow, Helwan, Cairo Governorate, Egypt", "lat": 29.812852, "lng": 31.3026883, "types": ["point_of_interest", "establishment"], "place_id": "ChIJ_____6s1WBQRwaapHh0lubA"}, {"name": "Ittihadia Palace", "formatted_address": "Al Nadi، El-Montaza, Heliopolis, Cairo Governorate, Egypt", "lat": 30.0888643, "lng": 31.3193929, "types": ["tourist_attraction", "premise", "point_of_interest", "establishment"], "place_id": "ChIJuftqUS8-WBQRtM7fDk0QcPk"}, {"name": "The Great Pyramid of Giza", "formatted_address": "Al Haram, Nazlet El-Semman, Al Giza Desert, Giza Governorate, Egypt", "lat": 29.9792345, "lng": 31.1342019, "types": ["tourist_attraction", "premise", "point_of_interest", "establishment"], "place_id": "ChIJGymPrIdFWBQRJCSloj8vDIE"}, {"name": "Baron Empain Palace", "formatted_address": "El-Orouba, El-Montaza, Heliopolis, Cairo Governorate 11757, Egypt", "lat": 30.0866701, "lng": 31.3303332, "types": ["point_of_interest", "establishment"], "place_id": "ChIJ1_GM8iE-WBQRLNVi-RT7vDA"}, {"name": "Maadi Island", "formatted_address": "Dar Al Salam, Giza Governorate, Egypt", "lat": 29.965527, "lng": 31.239237, "types": ["restaurant", "tourist_attraction", "park", "food", "point_of_interest", "establishment"], "place_id": "ChIJwY7d5MFHWBQRl1nMXlW_tUY"}, {"name": "Our Lady of Heliopolis Co-Cathedral", "formatted_address": "Nazih Khalifa crossroad، Al Ahram, Heliopolis, Cairo Governorate, Egypt", "lat": 30.0935707, "lng": 31.3251828, "types": ["church", "place_of_worship", "point_of_interest", "establishment"], "place_id": "ChIJJdgh-okVWBQR5TqTmKuQ0IM"}, {"name": "El Forsan", "formatted_address": "Kafr Al Olow, Qesm Helwan, Cairo Governorate, Egypt", "lat": 29.8093024, "lng": 31.3085111, "types": ["point_of_interest", "establishment"], "place_id": "ChIJlVaU0lQ0WBQRfBLWU46g-OQ"}, {"name": "خالد عويس", "formatted_address": "Helwan, Helwan Sharkeya, Helwan, Cairo Governorate, Egypt", "lat": 29.7991616, "lng": 31.3089826, "types": ["general_contractor", "point_of_interest", "establishment"], "place_id": "ChIJu9ZrORw1WBQRAEuKvbK8Vic"}, {"name": "Mahmoud Donya", "formatted_address": "Mansheyat Al Bakri, Heliopolis, Cairo Governorate, Egypt", "lat": 30.0892141, "lng": 31.3047596, "types": ["point_of_interest", "establishment"], "place_id": "ChIJGfIeaNI_WBQRiRRGKV6ZATU"}, {"name": "El Salam", "formatted_address": "Mansheyat Al Bakri, Heliopolis, Cairo Governorate, Egypt", "lat": 30.090121, "lng": 31.3049861, "types": ["point_of_interest", "establishment"], "place_id": "ChIJF6eGUdI_WBQRTPRhzCmsOJ8"}, {"name": "Porto Heliopolis", "formatted_address": "Almazah, Heliopolis, Cairo Governorate, Egypt", "lat": 30.0827031, "lng": 31.348709, "types": ["lodging", "point_of_interest", "establishment"], "place_id": "ChIJR5FCXgE-WBQR471eyuZuvGw"}, {"name": "Radisson Blu Hotel, Cairo Heliopolis", "formatted_address": "Abdel Hamid Badawi St Heliopolis, Cairo Governorate 11787, Egypt", "lat": 30.1065093, "lng": 31.3753121, "types": ["lodging", "point_of_interest", "establishment"], "place_id": "ChIJQZJ8fWUWWBQRAUPO9I6SxPg"}, {"name": "Heliopolis Towers Hotel", "formatted_address": "El Shaheed Sayed Zakaria, Sheraton Al Matar, El Nozha, Cairo Governorate 11736, Egypt", "lat": 30.1074763, "lng": 31.3661798, "types": ["lodging", "point_of_interest", "establishment"], "place_id": "ChIJZ9p3820WWBQRmZh2M_MSzOQ"}, {"name": "Citystars Heliopolis", "formatted_address": "Citystars, Cairo Governorate 11771, Egypt", "lat": 30.0728734, "lng": 31.3458082, "types": ["shopping_mall", "point_of_interest", "establishment"], "place_id": "ChIJo0ecE_gVWBQRGGrouhZFdME"}, {"name": "Specialized Gardens Project", "formatted_address": "Al Hadiqah Ad Dawleyah, Nasr City, Cairo Governorate, Egypt", "lat": 30.0474369, "lng": 31.3367616, "types": ["point_of_interest", "establishment"], "place_id": "ChIJyWtAHIo-WBQRnlrMUgb1eMI"}, {"name": "Elsmah", "formatted_address": "Mansheyat Al Bakri, Heliopolis, Cairo Governorate, Egypt", "lat": 30.0910008, "lng": 31.3050346, "types": ["point_of_interest", "establishment"], "place_id": "ChIJxY0Cr9M_WBQRrTLV4qQOPQs"}, {"name": "JW Marriott Hotel Cairo", "formatted_address": "Mirage City, Ring Rd, Second New Cairo, Cairo Governorate 11757, Egypt", "lat": 30.0719258, "lng": 31.434406, "types": ["lodging", "point_of_interest", "establishment"], "place_id": "ChIJ7x-mqic-WBQRN-Ml0uWwRcI"}, {"name": "SITES INTERNATIONAL | Landscape Architects of the Middle East", "formatted_address": "Al Mansoureya Rd, Zawya Abou Muslim, الجيزة، Giza Governorate 12561, Egypt", "lat": 29.946574, "lng": 31.151964, "types": ["local_government_office", "general_contractor", "point_of_interest", "establishment"], "place_id": "ChIJodNGmj5PWBQRCmW_XW3s0D4"}, {"name": "Golden Park Hotel", "formatted_address": "شارع الحجاز ، مصر الجديده، 221 شارع الحجاز ، هيليوبوليس ،، El Nozha, Cairo Governorate, Egypt", "lat": 30.1153686, "lng": 31.3525102, "types": ["lodging", "point_of_interest", "establishment"], "place_id": "ChIJsQQdRNgVWBQRss6fVxNFk_8"}, {"name": "ستوديو ذات", "formatted_address": "22 El-Khalifa El-Maamoun, Mansheya El-Bakry, Heliopolis, Cairo Governorate, Egypt", "lat": 30.0870556, "lng": 31.3038398, "types": ["point_of_interest", "establishment"], "place_id": "ChIJtYPJ680_WBQRlGibx417NdE"}, {"name": "Stodio 19", "formatted_address": "7 المقريزي، Mansheya El-Bakry, Heliopolis, Cairo Governorate, Egypt", "lat": 30.0893379, "lng": 31.3054145, "types": ["point_of_interest", "establishment"], "place_id": "ChIJu3kRX9I_WBQRE-mneNV_-Ec"}, {"name": "City For Arch Models", "formatted_address": "ش Mansheya El-Bakry, Heliopolis, Cairo Governorate, Egypt", "lat": 30.088441, "lng": 31.303395, "types": ["point_of_interest", "establishment"], "place_id": "ChIJqwjVB9I_WBQRlGpF1nLIUz0"}, {"name": "Easy Tech", "formatted_address": "9 Hasan Lotfy, Mansheya El-Bakry, Heliopolis, Cairo Governorate, Egypt", "lat": 30.0878892, "lng": 31.3054104, "types": ["point_of_interest", "establishment"], "place_id": "ChIJUTGuf9I_WBQRyxQ_1ZkXpZU"}, {"name": "Eilfia Law Firm", "formatted_address": "11351، 11 al tayar hassan lotfi street, Heliopolis, Cairo Government، Cairo Governorate 11351, Egypt", "lat": 30.0887267, "lng": 31.3054328, "types": ["lawyer", "point_of_interest", "establishment"], "place_id": "ChIJxUnIHbUVWBQRElOklimvTFk"}, {"name": "Wellness Clinic Dr. Wagih Sedky", "formatted_address": "El-Khalifa El-Maamoun, Mansheya El-Bakry, Heliopolis, Cairo Governorate, Egypt", "lat": 30.0870449, "lng": 31.3054627, "types": ["point_of_interest", "establishment"], "place_id": "ChIJiXuJ37o_WBQRZMd4kdKfWyc"}, {"name": "منال أحمد عبد اللطيف", "formatted_address": "شارع El-Khalifa El-Maamoun, حمامات القبة، Heliopolis, Cairo Governorate, Egypt", "lat": 30.0870941, "lng": 31.303934, "types": ["lawyer", "point_of_interest", "establishment"], "place_id": "ChIJtZSf680_WBQRzG7LucY8PxA"}, {"name": "El Barka Co. For Stationery Equipment", "formatted_address": "9 Lotfy, Mansheya El-Bakry, Heliopolis, Cairo Governorate, Egypt", "lat": 30.0878892, "lng": 31.3054104, "types": ["point_of_interest", "establishment"], "place_id": "ChIJUTGuf9I_WBQRMqphyAR6yhU"}, {"name": "Sigma Dent", "formatted_address": "9 Ahmed Lotfy El Sayed St.، ABBASSEYA، Heliopolis, Cairo Governorate, Egypt", "lat": 30.0878892, "lng": 31.3054104, "types": ["point_of_interest", "establishment"], "place_id": "ChIJUTGuf9I_WBQR5xrZf94mk9g"}, {"name": "El Zaeem Key", "formatted_address": "67 ش ابن سندر، سراى القبة، Heliopolis, Cairo Governorate, Egypt", "lat": 30.0896181, "lng": 31.3035809, "types": ["point_of_interest", "establishment"], "place_id": "ChIJj1R1PdI_WBQRj6kqw55VKKI"}, {"name": "مسجد أبو بخير بدر المقاول", "formatted_address": "المقريزي، حمامات القبة، Heliopolis, Cairo Governorate, Egypt", "lat": 30.0873008, "lng": 31.3044542, "types": ["mosque", "place_of_worship", "point_of_interest", "establishment"], "place_id": "ChIJRR4cks0_WBQRlXxOl-aBAwk"}, {"name": "Abu El Khair Masjed", "formatted_address": "El-Khalifa El-Maamoun, Mansheya El-Bakry, Heliopolis, Cairo Governorate, Egypt", "lat": 30.0871765, "lng": 31.3044665, "types": ["mosque", "place_of_worship", "point_of_interest", "establishment"], "place_id": "ChIJNzJxlM0_WBQRuVnnpOPeF9Q"}, {"name": "Housing Fund armed forces", "formatted_address": "Ewais, Mansheya El-Bakry, Heliopolis, Cairo Governorate, Egypt", "lat": 30.0863959, "lng": 31.3045118, "types": ["point_of_interest", "establishment"], "place_id": "ChIJN-33ks0_WBQRIV7bRgReznM"}, {"name": "مكتب د.محمود عبد الفتاح", "formatted_address": "Hasan Lotfy, حمامات القبة، Heliopolis, Cairo Governorate, Egypt", "lat": 30.0889562, "lng": 31.3054927, "types": ["lawyer", "point_of_interest", "establishment"], "place_id": "ChIJ0zQWYNI_WBQRW-AeS7DJKv4"}, {"name": "El Magd For Supplies", "formatted_address": "12 ميدان بن سندر، El-Zaytoun Sharkeya, Zeitoun, Cairo Governorate, Egypt", "lat": 30.0896181, "lng": 31.3035809, "types": ["point_of_interest", "establishment"], "place_id": "ChIJb8H0PNI_WBQRQGhHVb1umzA"}, {"name": "Youth Athletic club of Mansheyet el Bakrey", "formatted_address": "Mansheya El-Bakry, Heliopolis, Cairo Governorate, Egypt", "lat": 30.0892618, "lng": 31.3054404, "types": ["point_of_interest", "establishment"], "place_id": "ChIJbz-2x_s_WBQRkNcHQYmJULI"}, {"name": "Spiroplastic", "formatted_address": "شارع منشية البكرى، الحمام، El-Qobba, Heliopolis, Cairo Governorate, Egypt", "lat": 30.0886873, "lng": 31.3042957, "types": ["point_of_interest", "store", "establishment"], "place_id": "ChIJh4SActI_WBQRIaPWBmU6UDE"}, {"name": "المصرية الدولية للإستشارات القانونية", "formatted_address": "11A Hasan Lotfy, Mansheya El-Bakry, Heliopolis, Cairo Governorate 11351, Egypt", "lat": 30.0889512, "lng": 31.3054415, "types": ["point_of_interest", "establishment"], "place_id": "ChIJJca_XoM_WBQR6cCIipF0W0w"}, {"name": "Alkasr", "formatted_address": "7 Ewais, Mansheya El-Bakry, Heliopolis, Cairo Governorate, Egypt", "lat": 30.0887854, "lng": 31.30443129999999, "types": ["store", "point_of_interest", "establishment"], "place_id": "ChIJLWQBbdI_WBQRyMjIuP0jo84"}, {"name": "دار مسنين الإحسان", "formatted_address": "الخليفة المأمون، منشية البكري، قسم مصر الجديدة، محافظة القاهرة‬،، Egypt", "lat": 30.0883241, "lng": 31.3047444, "types": ["lodging", "point_of_interest", "establishment"], "place_id": "ChIJ5R37rc8_WBQRWN5Sk_t1udc"}, {"name": "Triumph Plaza Hotel", "formatted_address": "Intersection Of Ihsan Abdel Kodous St. with, El-Khalifa El-Maamoun, st, Cairo Governorate 11757, Egypt", "lat": 30.0864639, "lng": 31.3060439, "types": ["lodging", "point_of_interest", "establishment"], "place_id": "ChIJdQaFc80_WBQRaTzpSBv1-BQ"}, {"name": "InterContinental Citystars Cairo, an IHG Hotel", "formatted_address": "Omar Ibn El Khattab، Street، Cairo Governorate 11737, Egypt", "lat": 30.0724583, "lng": 31.3478955, "types": ["lodging", "point_of_interest", "establishment"], "place_id": "ChIJJYCniw4-WBQRDaNySSZ_iuI"}, {"name": "Heliopolis Developers Group", "formatted_address": "شارع Makram Ebeid, Al Manteqah as Sadesah, Nasr City, Cairo Governorate 11762, Egypt", "lat": 30.06249639999999, "lng": 31.3446167, "types": ["general_contractor", "point_of_interest", "establishment"], "place_id": "ChIJY-NFOnI-WBQRv7lSZBvESCY"}, {"name": "Computer & Communication Concept - C & CC", "formatted_address": "6 Aflaton St.، Masaken Al Mohandesin, Heliopolis, Cairo Governorate, Egypt", "lat": 30.079575, "lng": 31.344988, "types": ["point_of_interest", "establishment"], "place_id": "ChIJVznwLfEVWBQR_2KCGtndzME"}, {"name": "Abou Mohamed Ewais", "formatted_address": "Qesm Al Fayoum, Faiyum, Faiyum Governorate, Egypt", "lat": 29.3084021, "lng": 30.8428497, "types": ["point_of_interest", "establishment"], "place_id": "ChIJOakyPS95WRQRGBaTuq-ScSE"}, {"name": "Church of the Great Martyr Saint George and Anba Ebram - كنيسة الشهيد العظيم مارجرجس و الأنبا ابرآم", "formatted_address": "54 Abd El-Aziz Fahmy, Al Matar, El Nozha, Cairo Governorate, Egypt", "lat": 30.1080494, "lng": 31.3392792, "types": ["church", "place_of_worship", "point_of_interest", "establishment"], "place_id": "ChIJvzrXsekVWBQRye4OpOsJnNM"}, {"name": "TOLIP El Galaa - Heliopolis", "formatted_address": "El Orouba St, Sheraton Al Matar, El Nozha, Cairo Governorate, Egypt", "lat": 30.0985969, "lng": 31.3490226, "types": ["lodging", "point_of_interest", "establishment"], "place_id": "ChIJvyeGu-QVWBQRkPqc2rg6IsE"}, {"name": "Dr. Ibrahim Ewais", "formatted_address": "8 El Gomhoureya St.، DOWNTOWN، Abdeen, Cairo Governorate, Egypt", "lat": 30.045377, "lng": 31.246317, "types": ["doctor", "health", "point_of_interest", "establishment"], "place_id": "ChIJ7wZN7rtAWBQR95FA3glYbTU"}, {"name": "Hilton Cairo Heliopolis", "formatted_address": "El-Orouba, Sheraton Al Matar, El Nozha, Cairo Governorate, Egypt", "lat": 30.1067298, "lng": 31.3646213, "types": ["lodging", "point_of_interest", "establishment"], "place_id": "ChIJUYFpLCELRRQRzCxbUHFt6Vs"}, {"name": "Sites International", "formatted_address": "Al Mansoureya Rd, Zawya Abou Muslim, الجيزة، Giza Governorate, Egypt", "lat": 29.9465739, "lng": 31.1519641, "types": ["point_of_interest", "establishment"], "place_id": "ChIJm9NGmj5PWBQRENIQFD0XGjs"}, {"name": "Sonesta Hotel Tower & Casino Cairo", "formatted_address": "3 El Tayaran St, Ash Sharekat, Nasr City, Cairo Governorate, Egypt", "lat": 30.0789591, "lng": 31.3175599, "types": ["casino", "lodging", "point_of_interest", "establishment"], "place_id": "ChIJKYApCUc-WBQROTn4JL8ozhI"}, {"name": "Baron Hotel Heliopolis", "formatted_address": "14 Al Baroon, El-Montaza, Heliopolis, Cairo Governorate, Egypt", "lat": 30.0860748, "lng": 31.3314609, "types": ["lodging", "point_of_interest", "establishment"], "place_id": "ChIJUbVOACI-WBQRWsi5B7gYfxs"}, {"name": "PadelPod Club 7", "formatted_address": "1 rd. 210،, Maadi as Sarayat Al Gharbeyah, Maadi, Cairo Governorate, Egypt", "lat": 29.9621031, "lng": 31.2723583, "types": ["point_of_interest", "establishment"], "place_id": "ChIJR-7mddE5WBQRzuLZCRilAvU"}, {"name": "Heliopolis Sporting Club (HSC)", "formatted_address": "17 El-Sayed El-Marghany, Mansheya El-Bakry, Heliopolis, Cairo Governorate, Egypt", "lat": 30.0883155, "lng": 31.3164398, "types": ["point_of_interest", "establishment"], "place_id": "ChIJB9zy8B4-WBQRz_zRpJte8sA"}, {"name": "Cairo International Airport", "formatted_address": "Oruba، Road، El Nozha, Cairo Governorate, Egypt", "lat": 30.1128268, "lng": 31.3997904, "types": ["airport", "point_of_interest", "establishment"], "place_id": "ChIJQU-oLggXWBQRhhPiUSGvZeA"}, {"name": "(Heliopolis Public library)", "formatted_address": "Beirut, Almazah, Heliopolis, Cairo Governorate, Egypt", "lat": 30.090914, "lng": 31.3328428, "types": ["library", "point_of_interest", "establishment"], "place_id": "ChIJd3h9YvUVWBQR2Oi9DLQTI8E"}, {"name": "Cleopatra Hospitals Group", "formatted_address": "El-Saada St., El-Basatin Sharkeya, El Basatin, Cairo Governorate, Egypt", "lat": 29.9821264, "lng": 31.3209019, "types": ["point_of_interest", "establishment"], "place_id": "ChIJxRHdH-I5WBQRqddhKSTpzi8"}, {"name": "Post Office - West Heliopolis", "formatted_address": "El-Nozha, El Nozha, Cairo Governorate, Egypt", "lat": 30.1036179, "lng": 31.33018539999999, "types": ["post_office", "finance", "point_of_interest", "establishment"], "place_id": "ChIJ-1tRxpIVWBQR8pyCMmqAgXM"}, {"name": "Khattab Paper Point", "formatted_address": "4 ش صلاح الدين، Almazah, Heliopolis, Cairo Governorate, Egypt", "lat": 30.0918, "lng": 31.3341, "types": ["point_of_interest", "establishment"], "place_id": "ChIJx9lCdfUVWBQRkBpdq15VFcs"}, {"name": "IDP Education & IELTS Testing - Cairo", "formatted_address": "31 Omar Bekir St off Othman Ibn Afan St, Othman Ibn Affan, Nozha, Cairo Governorate 11361, Egypt", "lat": 30.10399, "lng": 31.348553, "types": ["point_of_interest", "establishment"], "place_id": "ChIJYWJmM-EVWBQRsRn2yOGljFo"}, {"name": "Le Passage Cairo Hotel & Casino", "formatted_address": "Sheraton Al Matar, El Nozha, Cairo Governorate 11861, Egypt", "lat": 30.1224496, "lng": 31.4005995, "types": ["lodging", "point_of_interest", "establishment"], "place_id": "ChIJ756gegIXWBQRvIob1vsKaiU"}]